optimiser.cpython-312-darwin.so
sauvola.cpython-312-darwin.so
archive_pdf_tools-1.5.7.data/scripts/recode_pdf
archive_pdf_tools-1.5.7.data/scripts/epub-to-pdf
archive_pdf_tools-1.5.7.data/scripts/pdf-metadata-json
archive_pdf_tools-1.5.7.data/scripts/pdfcomp
archive_pdf_tools-1.5.7.data/scripts/compress-pdf-images
internetarchivepdf/grayconvert.py
internetarchivepdf/__init__.py
internetarchivepdf/pdfrenderer.py
internetarchivepdf/pagenumbers.py
internetarchivepdf/recode.py
internetarchivepdf/pdfhacks.py
internetarchivepdf/mrc.py
internetarchivepdf/jpeg2000.py
internetarchivepdf/scandata.py
internetarchivepdf/const.py
internetarchivepdf/data/tesseract.ttf
internetarchivepdf/data/tmp.icc
archive_pdf_tools-1.5.7.dist-info/RECORD
archive_pdf_tools-1.5.7.dist-info/WHEEL
archive_pdf_tools-1.5.7.dist-info/top_level.txt
archive_pdf_tools-1.5.7.dist-info/METADATA
archive_pdf_tools-1.5.7.dist-info/licenses/LICENSE
archive_pdf_tools-1.5.7.dist-info/licenses/LICENSE.txt
