Metadata-Version: 2.4
Name: archive-pdf-tools
Version: 1.5.7
Summary: Internet Archive PDF compression tools
Home-page: https://github.com/internetarchive/archive-pdf-tools
Download-URL: https://github.com/internetarchive/archive-pdf-tools/archive/1.5.7.tar.gz
Author: Merlijn Boris Wolf Wajer
Author-email: merlijn@archive.org
License: AGPL-3.0
Keywords: PDF,MRC,hOCR,Internet Archive
Classifier: Development Status :: 3 - Alpha
Classifier: Intended Audience :: Developers
Classifier: License :: OSI Approved :: GNU Affero General Public License v3
Classifier: Programming Language :: Python :: 3
Requires-Python: >=3.6
License-File: LICENSE
License-File: LICENSE.txt
Requires-Dist: PyMuPDF>=1.19
Requires-Dist: Pillow>=8.3
Requires-Dist: archive_hocr_tools>=1.1.41
Requires-Dist: xmltodict>=0.12
Requires-Dist: roman>=3.3
Requires-Dist: numpy
Requires-Dist: lxml
Requires-Dist: scikit-image
Requires-Dist: PyWavelets
Requires-Dist: importlib_resources
Provides-Extra: docs
Requires-Dist: sphinx>=3; extra == "docs"
Dynamic: download-url
Dynamic: license-file
